{
  "formatVersion": 1,
  "database": {
    "version": 5,
    "identityHash": "c1c197998dc90dde76bfed2cc335697e",
    "entities": [
      {
        "tableName": "ToDo",
        "createSql": "CREATE TABLE IF NOT EXISTS `${TABLE_NAME}` (`name` TEXT, `description` TEXT, `checked` INTEGER NOT NULL, `contactIds` TEXT, `id` INTEGER PRIMARY KEY AUTOINCREMENT NOT NULL)",
        "fields": [
          {
            "fieldPath": "name",
            "columnName": "name",
            "affinity": "TEXT",
            "notNull": false
          },
          {
            "fieldPath": "description",
            "columnName": "description",
            "affinity": "TEXT",
            "notNull": false
          },
          {
            "fieldPath": "checked",
            "columnName": "checked",
            "affinity": "INTEGER",
            "notNull": true
          },
          {
            "fieldPath": "contactIds",
            "columnName": "contactIds",
            "affinity": "TEXT",
            "notNull": false
          },
          {
            "fieldPath": "id",
            "columnName": "id",
            "affinity": "INTEGER",
            "notNull": true
          }
        ],
        "primaryKey": {
          "columnNames": [
            "id"
          ],
          "autoGenerate": true
        },
        "indices": [],
        "foreignKeys": []
      }
    ],
    "views": [],
    "setupQueries": [
      "CREATE TABLE IF NOT EXISTS room_master_table (id INTEGER PRIMARY KEY,identity_hash TEXT)",
      "INSERT OR REPLACE INTO room_master_table (id,identity_hash) VALUES(42, 'c1c197998dc90dde76bfed2cc335697e')"
    ]
  }
}